lasso/__init__.py
lasso/logger.py
lasso/parameters.py
lasso/project.py
lasso/roadway.py
lasso/transit.py
lasso/util.py
wrangler_lasso-0.0.1.dist-info/LICENSE
wrangler_lasso-0.0.1.dist-info/METADATA
wrangler_lasso-0.0.1.dist-info/WHEEL
wrangler_lasso-0.0.1.dist-info/top_level.txt
wrangler_lasso-0.0.1.dist-info/RECORD
