Metadata-Version: 2.1
Name: wrangler-lasso
Version: 0.0.1
Summary: UNKNOWN
Home-page: https://github.com/wsp-sag/Lasso
License: Apache 2
Platform: any
Requires-Dist: lark-parser
Requires-Dist: pandas (<0.26)
Requires-Dist: jupyter
Requires-Dist: notebook
Requires-Dist: pytest
Requires-Dist: recommonmark
Requires-Dist: sphinx
Requires-Dist: sphinx-autodoc-typehints
Requires-Dist: sphinx-rtd-theme
Requires-Dist: black
